CaesarsCipher.py
CaesarsCipher-1.0.0.dist-info/LICENSE.txt
CaesarsCipher-1.0.0.dist-info/METADATA
CaesarsCipher-1.0.0.dist-info/WHEEL
CaesarsCipher-1.0.0.dist-info/top_level.txt
CaesarsCipher-1.0.0.dist-info/RECORD
