Metadata-Version: 2.1
Name: CaesarsCipher
Version: 1.0.0
Summary: This is a simple python package for encrypting and decrypting text in Caesar’s Cipher.
Home-page: UNKNOWN
Author: Aaron Fritz
Author-email: neversaydie2302@gmail.com
License: UNKNOWN
Platform: UNKNOWN
Classifier: Programming Language :: Python :: 3.6
Classifier: Programming Language :: Python :: 3.7
Classifier: Programming Language :: Python :: 3.8
Classifier: Programming Language :: Python :: 3.9
Classifier: Programming Language :: Python :: 3.10
Classifier: Topic :: Security :: Cryptography
Classifier: License :: OSI Approved :: MIT License
Classifier: Operating System :: OS Independent
License-File: LICENSE.txt
